woo/__init__.py
woo/ccxt/__init__.py
woo/ccxt/woo.py
woo/ccxt/abstract/woo.py
woo/ccxt/async_support/__init__.py
woo/ccxt/async_support/woo.py
woo/ccxt/async_support/base/__init__.py
woo/ccxt/async_support/base/exchange.py
woo/ccxt/async_support/base/throttler.py
woo/ccxt/async_support/base/ws/__init__.py
woo/ccxt/async_support/base/ws/cache.py
woo/ccxt/async_support/base/ws/client.py
woo/ccxt/async_support/base/ws/functions.py
woo/ccxt/async_support/base/ws/future.py
woo/ccxt/async_support/base/ws/order_book.py
woo/ccxt/async_support/base/ws/order_book_side.py
woo/ccxt/base/__init__.py
woo/ccxt/base/decimal_to_precision.py
woo/ccxt/base/errors.py
woo/ccxt/base/exchange.py
woo/ccxt/base/precise.py
woo/ccxt/base/types.py
woo/ccxt/pro/__init__.py
woo/ccxt/pro/woo.py
woo/ccxt/static_dependencies/README.md
woo/ccxt/static_dependencies/__init__.py
woo/ccxt/static_dependencies/bip/__init__.py
woo/ccxt/static_dependencies/bip/addr/P2PKH_addr.py
woo/ccxt/static_dependencies/bip/addr/__init__.py
woo/ccxt/static_dependencies/bip/addr/addr_dec_utils.py
woo/ccxt/static_dependencies/bip/addr/addr_key_validator.py
woo/ccxt/static_dependencies/bip/addr/iaddr_decoder.py
woo/ccxt/static_dependencies/bip/addr/iaddr_encoder.py
woo/ccxt/static_dependencies/bip/base58/__init__.py
woo/ccxt/static_dependencies/bip/base58/base58.py
woo/ccxt/static_dependencies/bip/base58/base58_ex.py
woo/ccxt/static_dependencies/bip/base58/base58_xmr.py
woo/ccxt/static_dependencies/bip/bech32/__init__.py
woo/ccxt/static_dependencies/bip/bech32/bch_bech32.py
woo/ccxt/static_dependencies/bip/bech32/bech32.py
woo/ccxt/static_dependencies/bip/bech32/bech32_base.py
woo/ccxt/static_dependencies/bip/bech32/bech32_ex.py
woo/ccxt/static_dependencies/bip/bech32/segwit_bech32.py
woo/ccxt/static_dependencies/bip/bip32/__init__.py
woo/ccxt/static_dependencies/bip/bip32/bip32_const.py
woo/ccxt/static_dependencies/bip/bip32/bip32_ex.py
woo/ccxt/static_dependencies/bip/bip32/bip32_key_data.py
woo_api-0.0.117.dist-info/METADATA
woo_api-0.0.117.dist-info/WHEEL
woo_api-0.0.117.dist-info/RECORD
